README.md
setup.cfg
setup.py
dsnd_probability_MLAws/Binomialdistribution.py
dsnd_probability_MLAws/Gaussiandistribution.py
dsnd_probability_MLAws/Generaldistribution.py
dsnd_probability_MLAws/__init__.py
dsnd_probability_MLAws.egg-info/PKG-INFO
dsnd_probability_MLAws.egg-info/SOURCES.txt
dsnd_probability_MLAws.egg-info/dependency_links.txt
dsnd_probability_MLAws.egg-info/not-zip-safe
dsnd_probability_MLAws.egg-info/top_level.txt