Metadata-Version: 1.0
Name: dsnd-probability-MLAws
Version: 0.1
Summary: Gaussian and Binomial distributions dsnd_probability_MLAws
Home-page: UNKNOWN
Author: Marwan Alsharabbi
Author-email: marwanalsharabbi@gmail.com
License: UNKNOWN
Platform: UNKNOWN
